dLux/__init__.py
dLux/detectors.py
dLux/instruments.py
dLux/optical_systems.py
dLux/psfs.py
dLux/sources.py
dLux/spectra.py
dLux/transformations.py
dLux/wavefronts.py
dLux/dev/FFTfresnel.py
dLux/dev/Filters.py
dLux/dev/fourier_rotate.py
dLux/layers/__init__.py
dLux/layers/aberrations.py
dLux/layers/apertures.py
dLux/layers/detector_layers.py
dLux/layers/optical_layers.py
dLux/layers/optics.py
dLux/layers/propagators.py
dLux/layers/unified_layers.py
dLux/utils/__init__.py
dLux/utils/array_ops.py
dLux/utils/coordinates.py
dLux/utils/geometry.py
dLux/utils/helpers.py
dLux/utils/interpolation.py
dLux/utils/math.py
dLux/utils/optics.py
dLux/utils/propagation.py
dLux/utils/source.py
dLux/utils/units.py
dLux/utils/zernikes.py
dlux-0.14.1.dist-info/licenses/LICENSE.md
dlux-0.14.1.dist-info/METADATA
dlux-0.14.1.dist-info/WHEEL
dlux-0.14.1.dist-info/top_level.txt
dlux-0.14.1.dist-info/RECORD
