Metadata-Version: 2.4
Name: dLux
Version: 0.14.1
Summary: Differentiable Optical Models as Parameterised Neural Networks in Jax using Zodiax.
Author-email: Louis Desdoigts <louis.desdoigts@sydney.edu.au>
License: BSD 3-Clause License
Project-URL: repository, https://github.com/LouisDesdoigts/dLux
Keywords: python,optics,machine-learning,jax,autodiff,differentiable,diffraction,simulation,telescope,dLux
Classifier: Programming Language :: Python :: 3
Classifier: Operating System :: OS Independent
Requires-Python: >=3.8
License-File: LICENSE.md
Requires-Dist: jax
Requires-Dist: jaxlib
Requires-Dist: zodiax>=0.4.1
Provides-Extra: extras
Requires-Dist: matplotlib; extra == "extras"
Requires-Dist: jupyter; extra == "extras"
Requires-Dist: jupyterlab; extra == "extras"
Requires-Dist: tqdm; extra == "extras"
Requires-Dist: chainconsumer; extra == "extras"
Requires-Dist: numpyro; extra == "extras"
Requires-Dist: dLuxToliman; extra == "extras"
Requires-Dist: scikit-learn; extra == "extras"
Provides-Extra: dev
Requires-Dist: pytest; extra == "dev"
Requires-Dist: black; extra == "dev"
Requires-Dist: ruff; extra == "dev"
Requires-Dist: pre-commit; extra == "dev"
Requires-Dist: mkdocs; extra == "dev"
Requires-Dist: mkdocs-jupyter; extra == "dev"
Requires-Dist: mkdocs-same-dir; extra == "dev"
Requires-Dist: mkdocs-autorefs; extra == "dev"
Requires-Dist: mkdocs-simple-plugin; extra == "dev"
Requires-Dist: mkdocstrings-python; extra == "dev"
Requires-Dist: jupyter_contrib_nbextensions; extra == "dev"
Requires-Dist: notebook==6.4.12; extra == "dev"
Dynamic: license-file
